Workbook
Name AgenticDict: Dictionary!$A$2:$A$177
Name AgenticTerm: Dictionary!$F$2:$F$155
Name CommunalDict: Dictionary!$B$2:$B$103
Name CommunalTerm: Dictionary!$G$2:$G$119
Name NegativeDict: Dictionary!$D$2:$D$22
Name NeutralDict: Dictionary!$C$2:$C$42
Name NeutralTerm: Dictionary!$E$2:$E$55

Sheet Final
A1: Base_CV_ID | B1: Field | C1: Framing | D1: Cover_Letter | E1: Agentic_Count | F1: Communal_Count | G1: Neutral_Count | H1: Negative_Count | I1: Total_Words | J1: Count_Percent | K1: AC_Percent | L1: Similarity | M1: Status
A2: 1 | B2: Sales / Business Development | C2: Agentic | D2: Dear Hiring Manager, I am writing to express my strong interest in the Sales Executive position at your company. As a professional specialized in market expansion and customer management, I am eager to take full ownership of the operational responsibilities outlined for this role. In my previous position, my daily duties involved managing customer accounts, tracking regional industry metrics, and executing established sales processes to achieve the quarterly quota. I leverage standard CRM software to optimize operational data, resolve complex issues, and ensure that specific customer requirements are accurately documented. My proactive approach to communication focuses on presenting clear product presentations and delivering technical information to help stakeholders execute their purchasing action. Enclosed is my resume, which delivers additional details regarding my qualifications and specialization. I welcome the opportunity for an interview to demonstrate how my expertise will bring immediate value to your organization. Thank you for your time and consideration. Regards, [Your Name] | E2: {=SUMPRODUCT(ISNUMBER(SEARCH(AgenticDict, D2))*1)} -> 9 | F2: {=SUMPRODUCT(ISNUMBER(SEARCH(CommunalDict, D2))*1)} -> 0 | G2: {=SUMPRODUCT(ISNUMBER(SEARCH(NeutralDict, D2))*1)} -> 23 | H2: =SUMPRODUCT(ISNUMBER(SEARCH(NegativeDict, D2))*1) -> 0 | I2: =IF(LEN(TRIM(D2))=0,0,LEN(TRIM(D2))-LEN(SUBSTITUTE(TRIM(D2)," ",""))+7) -> 154 | J2: =SUM( I2 / VLOOKUP(A2, BaseUP!A:H, 8, FALSE)*100) -> 106.94444 | K2: =IF($C2="Agentic",SUM(E2/I2*100),SUM(F2/I2*100)) -> 5.8441558 | L2: [] | M2: =IF(AND(J2<=112, J2>=90, K2<=10.5, K2>=4.5, L2="[]"), "Pass", "Fail") -> Pass
A3: 1 | B3: Sales / Business Development | C3: Communal | D3: Dear Hiring Manager, I am writing to submit my application for the Sales Executive position at your company. With my collection of education and work experience in business development and customer management, I look forward to dedicating myself to fulfill the responsibilities of this role. In my previous position, my daily duties involved developing client accounts alongside the team, tracking regional industry metrics, and develop along established sales processes to contribute to the quarterly quota. I utilize standard CRM software to log operational data, address issues together, and ensure that specific client requirements are supported and documented. My collaborative approach to communication focuses on explaining clear product presentations and sharing technical information to help partner stakeholders consider their purchasing actions. Enclosed is my resume, which shares additional details regarding my qualifications and skills. I welcome the opportunity for an interview to explore how my relational skills will support your organization. Thank you for your time and consideration. Sincerely, [Your Name] | E3: {=SUMPRODUCT(ISNUMBER(SEARCH(AgenticDict, D3))*1)} -> 0 | F3: {=SUMPRODUCT(ISNUMBER(SEARCH(CommunalDict, D3))*1)} -> 8 | G3: {=SUMPRODUCT(ISNUMBER(SEARCH(NeutralDict, D3))*1)} -> 27 | H3: =SUMPRODUCT(ISNUMBER(SEARCH(NegativeDict, D3))*1) -> 0 | I3: =IF(LEN(TRIM(D3))=0,0,LEN(TRIM(D3))-LEN(SUBSTITUTE(TRIM(D3)," ",""))+7) -> 160 | J3: =SUM( I3 / VLOOKUP(A3, BaseUP!A:H, 8, FALSE)*100) -> 111.11111 | K3: =IF($C3="Agentic",SUM(E3/I3*100),SUM(F3/I3*100)) -> 5 | L3: [] | M3: =IF(AND(J3<=112, J3>=90, K3<=10.5, K3>=4.5, L3="[]"), "Pass", "Fail") -> Pass
A4: 2 | B4: Sales / Business Development | C4: Agentic | D4: Dear Hiring Manager, Please accept this application for the Business Development Specialist role currently open within your organization. I have established specialized expertise in the commercial sector, where I have strategically spent several years identifying industry growth paths and monitoring market developments. My experience includes managing customer acquisition processes, conducting systematic reviews of industry data, and maintaining direct communication across internal and external groups. In my last assignment, I took ownership of identifying alignment between our product specifications and specific customer requirements, executing an optimized workflow from initial contract discussions to final signing. I am accustomed to leveraging performance tracking software and technology to report on account status and deliver operational information to the organization. I have attached my resume for your comprehensive review. I look forward to the possibility of a follow-up contact to schedule a discussion regarding my qualifications for this position. Regards, [Your Name] | E4: {=SUMPRODUCT(ISNUMBER(SEARCH(AgenticDict, D4))*1)} -> 10 | F4: {=SUMPRODUCT(ISNUMBER(SEARCH(CommunalDict, D4))*1)} -> 0 | G4: {=SUMPRODUCT(ISNUMBER(SEARCH(NeutralDict, D4))*1)} -> 22 | H4: =SUMPRODUCT(ISNUMBER(SEARCH(NegativeDict, D4))*1) -> 0 | I4: =IF(LEN(TRIM(D4))=0,0,LEN(TRIM(D4))-LEN(SUBSTITUTE(TRIM(D4)," ",""))+7) -> 148 | J4: =SUM( I4 / VLOOKUP(A4, BaseUP!A:H, 8, FALSE)*100) -> 106.47482 | K4: =IF($C4="Agentic",SUM(E4/I4*100),SUM(F4/I4*100)) -> 6.7567568 | L4: [] | M4: =IF(AND(J4<=112, J4>=90, K4<=10.5, K4>=4.5, L4="[]"), "Pass", "Fail") -> Pass
A5: 2 | B5: Sales / Business Development | C5: Communal | D5: Dear Hiring Manager, Please accept this application for the Business Development Specialist role currently open within your organization. I have built relevant experience in the commercial sector, where I have dedicated several years identifying industry growth paths and monitoring market developments. My experience includes supporting customer acquisition processes, conducting systematic reviews of industry data, and maintaining professional communication across internal and external teams. In my last assignment, I was responsible for building alignment between our product specifications and specific client requirements, ensuring a collaborated workflow from initial contract discussions to final signing. I am accustomed to using performance tracking software and technology to connect on account status and provide helpful information to the organization. I have attached my resume for your comprehensive review. I look forward to the possibility of a follow-up contact to schedule a discussion and share my qualifications for this position. Sincerely, [Your Name] | E5: {=SUMPRODUCT(ISNUMBER(SEARCH(AgenticDict, D5))*1)} -> 2 | F5: {=SUMPRODUCT(ISNUMBER(SEARCH(CommunalDict, D5))*1)} -> 8 | G5: {=SUMPRODUCT(ISNUMBER(SEARCH(NeutralDict, D5))*1)} -> 21 | H5: =SUMPRODUCT(ISNUMBER(SEARCH(NegativeDict, D5))*1) -> 0 | I5: =IF(LEN(TRIM(D5))=0,0,LEN(TRIM(D5))-LEN(SUBSTITUTE(TRIM(D5)," ",""))+7) -> 148 | J5: =SUM( I5 / VLOOKUP(A5, BaseUP!A:H, 8, FALSE)*100) -> 106.47482 | K5: =IF($C5="Agentic",SUM(E5/I5*100),SUM(F5/I5*100)) -> 5.4054054 | L5: [] | M5: =IF(AND(J5<=112, J5>=90, K5<=10.5, K5>=4.5, L5="[]"), "Pass", "Fail") -> Pass
A6: 3 | B6: Procurement / Sourcing / Supply Chain | C6: Agentic | D6: Dear Hiring Manager, I am writing to apply for the Procurement Officer position at your company. I have driven a strategic background in supply chain activities, with specialized expertise working with vendor, contract administration, and compliance monitoring. In my previous role, I took ownership of executing standard procurement processes, including verifying vendor qualifications and tracking adherence to strict technical requirements. I consistently checked data during pricing reviews to optimize performance and ensure purchases remained within the allocated departmental budget. Additionally, I negotiated terms for commercial agreements and managed quality across all supplier products to maintain full compliance with internal operating policies. My attached resume details my formal credentials and specific experience with enterprise resource planning software. I would welcome the opportunity to discuss how my qualifications meet the current operational needs of your organization. Thank you for your time and consideration. Regards, [Your Name] | E6: {=SUMPRODUCT(ISNUMBER(SEARCH(AgenticDict, D6))*1)} -> 10 | F6: {=SUMPRODUCT(ISNUMBER(SEARCH(CommunalDict, D6))*1)} -> 0 | G6: {=SUMPRODUCT(ISNUMBER(SEARCH(NeutralDict, D6))*1)} -> 20 | H6: =SUMPRODUCT(ISNUMBER(SEARCH(NegativeDict, D6))*1) -> 0 | I6: =IF(LEN(TRIM(D6))=0,0,LEN(TRIM(D6))-LEN(SUBSTITUTE(TRIM(D6)," ",""))+7) -> 144 | J6: =SUM( I6 / VLOOKUP(A6, BaseUP!A:H, 8, FALSE)*100) -> 109.92366 | K6: =IF($C6="Agentic",SUM(E6/I6*100),SUM(F6/I6*100)) -> 6.9444444 | L6: [] | M6: =IF(AND(J6<=112, J6>=90, K6<=10.5, K6>=4.5, L6="[]"), "Pass", "Fail") -> Pass
A7: 3 | B7: Procurement / Sourcing / Supply Chain | C7: Communal | D7: Dear Hiring Manager, I am writing to apply for the Procurement Officer position at your company. I have built a background in supply chain activities, with dedicated experience working with vendor, contract administration, and compliance monitoring. In my previous role, I was responsible for working standard procurement processes, including verifying vendor qualifications and supporting adherence to technical requirements. I regularly checked data during pricing reviews alongside internal teams to ensure purchases remained within the collective budget. Additionally, I collaborated to reach an agreement for commercial contracts and built trust across all supplier products to maintain full compliance with internal operating policies. My attached resume details my formal credentials and specific experience with enterprise resource planning software. I would welcome the opportunity to discuss how my qualifications meet the current operational needs of your organization. Thank you for your time and consideration. Sincerely, [Your Name] | E7: {=SUMPRODUCT(ISNUMBER(SEARCH(AgenticDict, D7))*1)} -> 0 | F7: {=SUMPRODUCT(ISNUMBER(SEARCH(CommunalDict, D7))*1)} -> 7 | G7: {=SUMPRODUCT(ISNUMBER(SEARCH(NeutralDict, D7))*1)} -> 20 | H7: =SUMPRODUCT(ISNUMBER(SEARCH(NegativeDict, D7))*1) -> 0 | I7: =IF(LEN(TRIM(D7))=0,0,LEN(TRIM(D7))-LEN(SUBSTITUTE(TRIM(D7)," ",""))+7) -> 144 | J7: =SUM( I7 / VLOOKUP(A7, BaseUP!A:H, 8, FALSE)*100) -> 109.92366 | K7: =IF($C7="Agentic",SUM(E7/I7*100),SUM(F7/I7*100)) -> 4.8611111 | L7: [] | M7: =IF(AND(J7<=112, J7>=90, K7<=10.5, K7>=4.5, L7="[]"), "Pass", "Fail") -> Pass
A8: 4 | B8: Procurement / Sourcing / Supply Chain | C8: Agentic | D8: Dear Hiring Manager, This letter is in reference to the Logistics Coordinator role currently available within your organization. My background includes strong technical training and experience in supply chain tracking, logistics, and inventory management. My professional focus is on executing high-caliber, driven workflow processes. In my last position, I managed inventory levels, optimized performance in shipment schedules, and coordinated tracking data using in-house logistics software. Whenever discrepancies arose, I utilized my problem-solving skills by tracking the variance back to its source. I executed tasks with others from warehouse operations and transportation to ensure that physical stock levels aligned exactly with system requirements. My qualifications are outlined in detail in the attached resume. Please feel free to contact me via the information provided to schedule a discussion regarding this position. Thank you for your review and consideration. Regards, [Your Name] | E8: {=SUMPRODUCT(ISNUMBER(SEARCH(AgenticDict, D8))*1)} -> 7 | F8: {=SUMPRODUCT(ISNUMBER(SEARCH(CommunalDict, D8))*1)} -> 0 | G8: {=SUMPRODUCT(ISNUMBER(SEARCH(NeutralDict, D8))*1)} -> 21 | H8: =SUMPRODUCT(ISNUMBER(SEARCH(NegativeDict, D8))*1) -> 0 | I8: =IF(LEN(TRIM(D8))=0,0,LEN(TRIM(D8))-LEN(SUBSTITUTE(TRIM(D8)," ",""))+7) -> 139 | J8: =SUM( I8 / VLOOKUP(A8, BaseUP!A:H, 8, FALSE)*100) -> 109.44882 | K8: =IF($C8="Agentic",SUM(E8/I8*100),SUM(F8/I8*100)) -> 5.0359712 | L8: [] | M8: =IF(AND(J8<=112, J8>=90, K8<=10.5, K8>=4.5, L8="[]"), "Pass", "Fail") -> Pass
A9: 4 | B9: Procurement / Sourcing / Supply Chain | C9: Communal | D9: Dear Hiring Manager, This letter is in reference to the Logistics Coordinator role currently available within your organization. My background includes technical training and joint experience in supply chain tracking, logistics, and inventory management. My professional focus is on maintaining stable, supportive workflow processes. In my last position, I assisted in managing inventory levels, shipment schedules, and tracking data alongside the team using in-house logistics software. Whenever discrepancies arose, I restored harmony by tracking the variance back to its source. I worked with others with a cooperative spirit from warehouse operations and transportation to ensure that physical stock levels aligned exactly with system requirements. My qualifications are outlined in detail in the attached resume. Please feel free to contact me via the information provided to schedule a discussion regarding this position. Thank you for your review and consideration. Sincerely, [Your Name] | E9: {=SUMPRODUCT(ISNUMBER(SEARCH(AgenticDict, D9))*1)} -> 1 | F9: {=SUMPRODUCT(ISNUMBER(SEARCH(CommunalDict, D9))*1)} -> 7 | G9: {=SUMPRODUCT(ISNUMBER(SEARCH(NeutralDict, D9))*1)} -> 20 | H9: =SUMPRODUCT(ISNUMBER(SEARCH(NegativeDict, D9))*1) -> 0 | I9: =IF(LEN(TRIM(D9))=0,0,LEN(TRIM(D9))-LEN(SUBSTITUTE(TRIM(D9)," ",""))+7) -> 141 | J9: =SUM( I9 / VLOOKUP(A9, BaseUP!A:H, 8, FALSE)*100) -> 111.02362 | K9: =IF($C9="Agentic",SUM(E9/I9*100),SUM(F9/I9*100)) -> 4.964539 | L9: [] | M9: =IF(AND(J9<=112, J9>=90, K9<=10.5, K9>=4.5, L9="[]"), "Pass", "Fail") -> Pass
A10: 5 | B10: Project Management / Programme Management | C10: Agentic | D10: Dear Hiring Manager, I am writing to express my interest in the Project Manager position at your company. I possess experience in corporate administration, where my focus is on tracking project deliverables, budgets, and maintaining project timelines. Throughout my career, I have effectively managed a project workflow from initial scope definition through to completion based on documented requirements. My daily tasks include executing main project schedules and tracking resource allocation against the budget using tracking software. In my previous assignments, I directed technical personnel and optimized performance across all milestones by adhering strictly to formal testing and verification compliance frameworks. My background includes specialized certification in standard project methodologies. Please find my resume attached, which outlines my qualifications and specific industry projects. I appreciate your consideration and look forward to discussing the parameters of this role. Regards, [Your Name] | E10: {=SUMPRODUCT(ISNUMBER(SEARCH(AgenticDict, D10))*1)} -> 7 | F10: {=SUMPRODUCT(ISNUMBER(SEARCH(CommunalDict, D10))*1)} -> 0 | G10: {=SUMPRODUCT(ISNUMBER(SEARCH(NeutralDict, D10))*1)} -> 18 | H10: =SUMPRODUCT(ISNUMBER(SEARCH(NegativeDict, D10))*1) -> 0 | I10: =IF(LEN(TRIM(D10))=0,0,LEN(TRIM(D10))-LEN(SUBSTITUTE(TRIM(D10)," ",""))+7) -> 140 | J10: =SUM( I10 / VLOOKUP(A10, BaseUP!A:H, 8, FALSE)*100) -> 101.44928 | K10: =IF($C10="Agentic",SUM(E10/I10*100),SUM(F10/I10*100)) -> 5 | L10: [] | M10: =IF(AND(J10<=112, J10>=90, K10<=10.5, K10>=4.5, L10="[]"), "Pass", "Fail") -> Pass
A11: 5 | B11: Project Management / Programme Management | C11: Communal | D11: Dear Hiring Manager, I am writing to express my interest in the Project Manager position at your company. I possess cooperative experience in corporate administration, where my shared focus is on tracking project deliverables, budgets, and maintaining project timelines. Throughout my career, I have successfully looked after a project workflow as a collaborative effort from initial scope definition through to completion based on documented requirements. My daily tasks include updating main project schedules and tracking resource allocation alongside the team using tracking software. In my previous assignments, I led a cohesive team of technical personnel and ensured supportive work across all milestones by adhering strictly to formal testing and verification compliance frameworks. My background includes specific certification in standard project methodologies. Please find my resume attached, which outlines my contribution, qualifications and specific industry projects. I sincerely appreciate your consideration and look forward to discussing the parameters of this role. Sincerely, [Your Name] | E11: {=SUMPRODUCT(ISNUMBER(SEARCH(AgenticDict, D11))*1)} -> 0 | F11: {=SUMPRODUCT(ISNUMBER(SEARCH(CommunalDict, D11))*1)} -> 8 | G11: {=SUMPRODUCT(ISNUMBER(SEARCH(NeutralDict, D11))*1)} -> 18 | H11: =SUMPRODUCT(ISNUMBER(SEARCH(NegativeDict, D11))*1) -> 0 | I11: =IF(LEN(TRIM(D11))=0,0,LEN(TRIM(D11))-LEN(SUBSTITUTE(TRIM(D11)," ",""))+7) -> 154 | J11: =SUM( I11 / VLOOKUP(A11, BaseUP!A:H, 8, FALSE)*100) -> 111.5942 | K11: =IF($C11="Agentic",SUM(E11/I11*100),SUM(F11/I11*100)) -> 5.1948052 | L11: [] | M11: =IF(AND(J11<=112, J11>=90, K11<=10.5, K11>=4.5, L11="[]"), "Pass", "Fail") -> Pass
A12: 6 | B12: Project Management / Programme Management | C12: Agentic | D12: Dear Hiring Manager, Please accept my application for the Programme Coordinator role within your organization. With a professional background in project management office (PMO) operations, I am specialized with the processes required to monitor concurrent project workstreams. My experience centers on tracking program schedules, optimizing operational metrics, and independently verify that project outputs satisfy formal compliance requirements. I proactively direct data analysis to generate accurate status reports for the organization. In this role, I executed tasks with others across different project departments and communicated insights regarding standard operating procedures to maintain consistency in scheduling and documentation formats. My resume is attached for your comprehensive review. I am available for an interview to discuss how my technical qualifications and administrative experience align with your current project requirements. Thank you for your consideration. Regards, [Your Name] | E12: {=SUMPRODUCT(ISNUMBER(SEARCH(AgenticDict, D12))*1)} -> 7 | F12: {=SUMPRODUCT(ISNUMBER(SEARCH(CommunalDict, D12))*1)} -> 1 | G12: {=SUMPRODUCT(ISNUMBER(SEARCH(NeutralDict, D12))*1)} -> 18 | H12: =SUMPRODUCT(ISNUMBER(SEARCH(NegativeDict, D12))*1) -> 0 | I12: =IF(LEN(TRIM(D12))=0,0,LEN(TRIM(D12))-LEN(SUBSTITUTE(TRIM(D12)," ",""))+7) -> 134 | J12: =SUM( I12 / VLOOKUP(A12, BaseUP!A:H, 8, FALSE)*100) -> 107.2 | K12: =IF($C12="Agentic",SUM(E12/I12*100),SUM(F12/I12*100)) -> 5.2238806 | L12: [] | M12: =IF(AND(J12<=112, J12>=90, K12<=10.5, K12>=4.5, L12="[]"), "Pass", "Fail") -> Pass
A13: 6 | B13: Project Management / Programme Management | C13: Communal | D13: Dear Hiring Manager, Please accept my application for the Programme Coordinator role within your organization. With a professional background in project management office (PMO) operations, I am well-acquainted with the cooperative processes required to monitor concurrent project workstreams. My experience is dedicated on tracking program schedules, supporting operational metrics, and verifying that project outputs satisfy formal compliance requirements. I routinely assisted with data to generate accurate status reports for the organization. In this role, I worked alongside the team across different project departments and communicated information regarding standard operating procedures to maintain consistency in scheduling and documentation formats. My resume is attached for your comprehensive review. I am available for an interview to share how my technical qualifications and administrative experience align with your current project requirements. Thank you for your consideration. Sincerely, [Your Name] | E13: {=SUMPRODUCT(ISNUMBER(SEARCH(AgenticDict, D13))*1)} -> 0 | F13: {=SUMPRODUCT(ISNUMBER(SEARCH(CommunalDict, D13))*1)} -> 7 | G13: {=SUMPRODUCT(ISNUMBER(SEARCH(NeutralDict, D13))*1)} -> 19 | H13: =SUMPRODUCT(ISNUMBER(SEARCH(NegativeDict, D13))*1) -> 0 | I13: =IF(LEN(TRIM(D13))=0,0,LEN(TRIM(D13))-LEN(SUBSTITUTE(TRIM(D13)," ",""))+7) -> 135 | J13: =SUM( I13 / VLOOKUP(A13, BaseUP!A:H, 8, FALSE)*100) -> 108 | K13: =IF($C13="Agentic",SUM(E13/I13*100),SUM(F13/I13*100)) -> 5.1851852 | L13: [] | M13: =IF(AND(J13<=112, J13>=90, K13<=10.5, K13>=4.5, L13="[]"), "Pass", "Fail") -> Pass
... A181: 90 | B181: Project Management / Programme Management | C181: Communal | D181: Dear Hiring Manager, I am writing to express interest in the Project Management position at [Company]. My professional background aligns with the requirements stated in the job description, and I am submitting my application for your consideration. My experience includes management of projects within [Location]. In previous roles, I collaborate on project timelines, maintained documentation, and tracked progress against collective goals. I have managed budgets and resources to ensure the contribution of assigned tasks through a cooperative approach. My skill set includes the use of project management software, data analysis, and technical reporting. I possess experience in risk assessment and assisting in the joint coordination of project phases. These skills allow for the mutual trust of schedules and the shared management of project documentation. I am available for an interview to discuss how my background meets the needs of [Company]. Please contact me via the information provided on my resume to arrange a time for further discussion. Thank you for your time and consideration of this application. Regards, [Your Name] | E181: {=SUMPRODUCT(ISNUMBER(SEARCH(AgenticDict, D181))*1)} -> 3 | F181: {=SUMPRODUCT(ISNUMBER(SEARCH(CommunalDict, D181))*1)} -> 11 | G181: {=SUMPRODUCT(ISNUMBER(SEARCH(NeutralDict, D181))*1)} -> 16 | H181: =SUMPRODUCT(ISNUMBER(SEARCH(NegativeDict, D181))*1) -> 0 | I181: =IF(LEN(TRIM(D181))=0,0,LEN(TRIM(D181))-LEN(SUBSTITUTE(TRIM(D181)," ",""))+7) -> 170 | J181: =SUM( I181 / VLOOKUP(A181, BaseUP!A:H, 8, FALSE)*100) -> 106.25 | K181: =IF($C181="Agentic",SUM(E181/I181*100),SUM(F181/I181*100)) -> 6.4705882 | L181: [] | M181: =IF(AND(J181<=112, J181>=90, K181<=10.5, K181>=4.5, L181="[]"), "Pass", "Fail") -> Pass

Sheet FinalBackup
A1: Base_CV_ID | B1: Field | C1: Framing | D1: Cover_Letter | E1: Agentic_Count | F1: Communal_Count | G1: Neutral_Count | H1: Negative_Count | I1: Total_Words | J1: Count_Percent | K1: AC_Percent | L1: Similarity | M1: Status
A2: 1 | B2: Sales / Business Development | C2: Agentic | D2: Dear Hiring Manager, I am writing to express my strong interest in the Sales Executive position at your company. As a professional specialized in market expansion and customer management, I am eager to take full ownership of the operational responsibilities outlined for this role. In my previous position, my daily duties involved managing customer accounts, tracking regional industry metrics, and executing established sales processes to achieve the quarterly quota. I leverage standard CRM software to optimize operational data, resolve complex issues, and ensure that specific customer requirements are accurately documented. My proactive approach to communication focuses on presenting clear product presentations and delivering technical information to help stakeholders execute their purchasing action. Enclosed is my resume, which delivers additional details regarding my qualifications and specialization. I welcome the opportunity for an interview to demonstrate how my expertise will bring immediate value to your organization. Thank you for your time and consideration. Regards, [Your Name] | E2: {=SUMPRODUCT(ISNUMBER(SEARCH(AgenticDict, D2))*1)} -> 9 | F2: {=SUMPRODUCT(ISNUMBER(SEARCH(CommunalDict, D2))*1)} -> 0 | G2: {=SUMPRODUCT(ISNUMBER(SEARCH(NeutralDict, D2))*1)} -> 23 | H2: =SUMPRODUCT(ISNUMBER(SEARCH(NegativeDict, D2))*1) -> 0 | I2: =IF(LEN(TRIM(D2))=0,0,LEN(TRIM(D2))-LEN(SUBSTITUTE(TRIM(D2)," ",""))+7) -> 154 | J2: =SUM( I2 / VLOOKUP(A2, BaseUP!A:H, 8, FALSE)*100) -> 106.94444 | K2: =IF($C2="Agentic",SUM(E2/I2*100),SUM(F2/I2*100)) -> 5.8441558 | L2: [] | M2: =IF(AND(J2<=112, J2>=90, K2<=10.5, K2>=4.5, L2="[]"), "Pass", "Fail") -> Pass
A3: 1 | B3: Sales / Business Development | C3: Communal | D3: Dear Hiring Manager, I am writing to submit my application for the Sales Executive position at your company. With my collection of education and work experience in business development and customer management, I look forward to dedicating myself to fulfill the responsibilities of this role. In my previous position, my daily duties involved developing client accounts alongside the team, tracking regional industry metrics, and develop along established sales processes to contribute to the quarterly quota. I utilize standard CRM software to log operational data, address issues together, and ensure that specific client requirements are supported and documented. My collaborative approach to communication focuses on explaining clear product presentations and sharing technical information to help partner stakeholders consider their purchasing actions. Enclosed is my resume, which shares additional details regarding my qualifications and skills. I welcome the opportunity for an interview to explore how my relational skills will support your organization. Thank you for your time and consideration. Sincerely, [Your Name] | E3: {=SUMPRODUCT(ISNUMBER(SEARCH(AgenticDict, D3))*1)} -> 0 | F3: {=SUMPRODUCT(ISNUMBER(SEARCH(CommunalDict, D3))*1)} -> 8 | G3: {=SUMPRODUCT(ISNUMBER(SEARCH(NeutralDict, D3))*1)} -> 27 | H3: =SUMPRODUCT(ISNUMBER(SEARCH(NegativeDict, D3))*1) -> 0 | I3: =IF(LEN(TRIM(D3))=0,0,LEN(TRIM(D3))-LEN(SUBSTITUTE(TRIM(D3)," ",""))+7) -> 160 | J3: =SUM( I3 / VLOOKUP(A3, BaseUP!A:H, 8, FALSE)*100) -> 111.11111 | K3: =IF($C3="Agentic",SUM(E3/I3*100),SUM(F3/I3*100)) -> 5 | L3: [] | M3: =IF(AND(J3<=112, J3>=90, K3<=10.5, K3>=4.5, L3="[]"), "Pass", "Fail") -> Pass
A4: 2 | B4: Sales / Business Development | C4: Agentic | D4: Dear Hiring Manager, Please accept this application for the Business Development Specialist role currently open within your organization. I have established specialized expertise in the commercial sector, where I have strategically spent several years identifying industry growth paths and monitoring market developments. My experience includes managing customer acquisition processes, conducting systematic reviews of industry data, and maintaining direct communication across internal and external groups. In my last assignment, I took ownership of identifying alignment between our product specifications and specific customer requirements, executing an optimized workflow from initial contract discussions to final signing. I am accustomed to leveraging performance tracking software and technology to report on account status and deliver operational information to the organization. I have attached my resume for your comprehensive review. I look forward to the possibility of a follow-up contact to schedule a discussion regarding my qualifications for this position. Regards, [Your Name] | E4: {=SUMPRODUCT(ISNUMBER(SEARCH(AgenticDict, D4))*1)} -> 10 | F4: {=SUMPRODUCT(ISNUMBER(SEARCH(CommunalDict, D4))*1)} -> 0 | G4: {=SUMPRODUCT(ISNUMBER(SEARCH(NeutralDict, D4))*1)} -> 22 | H4: =SUMPRODUCT(ISNUMBER(SEARCH(NegativeDict, D4))*1) -> 0 | I4: =IF(LEN(TRIM(D4))=0,0,LEN(TRIM(D4))-LEN(SUBSTITUTE(TRIM(D4)," ",""))+7) -> 148 | J4: =SUM( I4 / VLOOKUP(A4, BaseUP!A:H, 8, FALSE)*100) -> 106.47482 | K4: =IF($C4="Agentic",SUM(E4/I4*100),SUM(F4/I4*100)) -> 6.7567568 | L4: [] | M4: =IF(AND(J4<=112, J4>=90, K4<=10.5, K4>=4.5, L4="[]"), "Pass", "Fail") -> Pass
A5: 2 | B5: Sales / Business Development | C5: Communal | D5: Dear Hiring Manager, Please accept this application for the Business Development Specialist role currently open within your organization. I have built relevant experience in the commercial sector, where I have dedicated several years identifying industry growth paths and monitoring market developments. My experience includes supporting customer acquisition processes, conducting systematic reviews of industry data, and maintaining professional communication across internal and external teams. In my last assignment, I was responsible for building alignment between our product specifications and specific client requirements, ensuring a collaborated workflow from initial contract discussions to final signing. I am accustomed to using performance tracking software and technology to connect on account status and provide helpful information to the organization. I have attached my resume for your comprehensive review. I look forward to the possibility of a follow-up contact to schedule a discussion and share my qualifications for this position. Sincerely, [Your Name] | E5: {=SUMPRODUCT(ISNUMBER(SEARCH(AgenticDict, D5))*1)} -> 2 | F5: {=SUMPRODUCT(ISNUMBER(SEARCH(CommunalDict, D5))*1)} -> 8 | G5: {=SUMPRODUCT(ISNUMBER(SEARCH(NeutralDict, D5))*1)} -> 21 | H5: =SUMPRODUCT(ISNUMBER(SEARCH(NegativeDict, D5))*1) -> 0 | I5: =IF(LEN(TRIM(D5))=0,0,LEN(TRIM(D5))-LEN(SUBSTITUTE(TRIM(D5)," ",""))+7) -> 148 | J5: =SUM( I5 / VLOOKUP(A5, BaseUP!A:H, 8, FALSE)*100) -> 106.47482 | K5: =IF($C5="Agentic",SUM(E5/I5*100),SUM(F5/I5*100)) -> 5.4054054 | L5: [] | M5: =IF(AND(J5<=112, J5>=90, K5<=10.5, K5>=4.5, L5="[]"), "Pass", "Fail") -> Pass
A6: 3 | B6: Procurement / Sourcing / Supply Chain | C6: Agentic | D6: Dear Hiring Manager, I am writing to apply for the Procurement Officer position at your company. I have driven a strategic background in supply chain activities, with specialized expertise working with vendor, contract administration, and compliance monitoring. In my previous role, I took ownership of executing standard procurement processes, including verifying vendor qualifications and tracking adherence to strict technical requirements. I consistently checked data during pricing reviews to optimize performance and ensure purchases remained within the allocated departmental budget. Additionally, I negotiated terms for commercial agreements and managed quality across all supplier products to maintain full compliance with internal operating policies. My attached resume details my formal credentials and specific experience with enterprise resource planning software. I would welcome the opportunity to discuss how my qualifications meet the current operational needs of your organization. Thank you for your time and consideration. Regards, [Your Name] | E6: {=SUMPRODUCT(ISNUMBER(SEARCH(AgenticDict, D6))*1)} -> 10 | F6: {=SUMPRODUCT(ISNUMBER(SEARCH(CommunalDict, D6))*1)} -> 0 | G6: {=SUMPRODUCT(ISNUMBER(SEARCH(NeutralDict, D6))*1)} -> 20 | H6: =SUMPRODUCT(ISNUMBER(SEARCH(NegativeDict, D6))*1) -> 0 | I6: =IF(LEN(TRIM(D6))=0,0,LEN(TRIM(D6))-LEN(SUBSTITUTE(TRIM(D6)," ",""))+7) -> 144 | J6: =SUM( I6 / VLOOKUP(A6, BaseUP!A:H, 8, FALSE)*100) -> 109.92366 | K6: =IF($C6="Agentic",SUM(E6/I6*100),SUM(F6/I6*100)) -> 6.9444444 | L6: [] | M6: =IF(AND(J6<=112, J6>=90, K6<=10.5, K6>=4.5, L6="[]"), "Pass", "Fail") -> Pass
A7: 3 | B7: Procurement / Sourcing / Supply Chain | C7: Communal | D7: Dear Hiring Manager, I am writing to apply for the Procurement Officer position at your company. I have built a background in supply chain activities, with dedicated experience working with vendor, contract administration, and compliance monitoring. In my previous role, I was responsible for working standard procurement processes, including verifying vendor qualifications and supporting adherence to technical requirements. I regularly checked data during pricing reviews alongside internal teams to ensure purchases remained within the collective budget. Additionally, I collaborated to reach an agreement for commercial contracts and built trust across all supplier products to maintain full compliance with internal operating policies. My attached resume details my formal credentials and specific experience with enterprise resource planning software. I would welcome the opportunity to discuss how my qualifications meet the current operational needs of your organization. Thank you for your time and consideration. Sincerely, [Your Name] | E7: {=SUMPRODUCT(ISNUMBER(SEARCH(AgenticDict, D7))*1)} -> 0 | F7: {=SUMPRODUCT(ISNUMBER(SEARCH(CommunalDict, D7))*1)} -> 7 | G7: {=SUMPRODUCT(ISNUMBER(SEARCH(NeutralDict, D7))*1)} -> 20 | H7: =SUMPRODUCT(ISNUMBER(SEARCH(NegativeDict, D7))*1) -> 0 | I7: =IF(LEN(TRIM(D7))=0,0,LEN(TRIM(D7))-LEN(SUBSTITUTE(TRIM(D7)," ",""))+7) -> 144 | J7: =SUM( I7 / VLOOKUP(A7, BaseUP!A:H, 8, FALSE)*100) -> 109.92366 | K7: =IF($C7="Agentic",SUM(E7/I7*100),SUM(F7/I7*100)) -> 4.8611111 | L7: [] | M7: =IF(AND(J7<=112, J7>=90, K7<=10.5, K7>=4.5, L7="[]"), "Pass", "Fail") -> Pass
A8: 4 | B8: Procurement / Sourcing / Supply Chain | C8: Agentic | D8: Dear Hiring Manager, This letter is in reference to the Logistics Coordinator role currently available within your organization. My background includes strong technical training and experience in supply chain tracking, logistics, and inventory management. My professional focus is on executing high-caliber, driven workflow processes. In my last position, I managed inventory levels, optimized performance in shipment schedules, and coordinated tracking data using in-house logistics software. Whenever discrepancies arose, I utilized my problem-solving skills by tracking the variance back to its source. I executed tasks with others from warehouse operations and transportation to ensure that physical stock levels aligned exactly with system requirements. My qualifications are outlined in detail in the attached resume. Please feel free to contact me via the information provided to schedule a discussion regarding this position. Thank you for your review and consideration. Regards, [Your Name] | E8: {=SUMPRODUCT(ISNUMBER(SEARCH(AgenticDict, D8))*1)} -> 7 | F8: {=SUMPRODUCT(ISNUMBER(SEARCH(CommunalDict, D8))*1)} -> 0 | G8: {=SUMPRODUCT(ISNUMBER(SEARCH(NeutralDict, D8))*1)} -> 21 | H8: =SUMPRODUCT(ISNUMBER(SEARCH(NegativeDict, D8))*1) -> 0 | I8: =IF(LEN(TRIM(D8))=0,0,LEN(TRIM(D8))-LEN(SUBSTITUTE(TRIM(D8)," ",""))+7) -> 139 | J8: =SUM( I8 / VLOOKUP(A8, BaseUP!A:H, 8, FALSE)*100) -> 109.44882 | K8: =IF($C8="Agentic",SUM(E8/I8*100),SUM(F8/I8*100)) -> 5.0359712 | L8: [] | M8: =IF(AND(J8<=112, J8>=90, K8<=10.5, K8>=4.5, L8="[]"), "Pass", "Fail") -> Pass
A9: 4 | B9: Procurement / Sourcing / Supply Chain | C9: Communal | D9: Dear Hiring Manager, This letter is in reference to the Logistics Coordinator role currently available within your organization. My background includes technical training and joint experience in supply chain tracking, logistics, and inventory management. My professional focus is on maintaining stable, supportive workflow processes. In my last position, I assisted in managing inventory levels, shipment schedules, and tracking data alongside the team using in-house logistics software. Whenever discrepancies arose, I restored harmony by tracking the variance back to its source. I worked with others with a cooperative spirit from warehouse operations and transportation to ensure that physical stock levels aligned exactly with system requirements. My qualifications are outlined in detail in the attached resume. Please feel free to contact me via the information provided to schedule a discussion regarding this position. Thank you for your review and consideration. Sincerely, [Your Name] | E9: {=SUMPRODUCT(ISNUMBER(SEARCH(AgenticDict, D9))*1)} -> 1 | F9: {=SUMPRODUCT(ISNUMBER(SEARCH(CommunalDict, D9))*1)} -> 7 | G9: {=SUMPRODUCT(ISNUMBER(SEARCH(NeutralDict, D9))*1)} -> 20 | H9: =SUMPRODUCT(ISNUMBER(SEARCH(NegativeDict, D9))*1) -> 0 | I9: =IF(LEN(TRIM(D9))=0,0,LEN(TRIM(D9))-LEN(SUBSTITUTE(TRIM(D9)," ",""))+7) -> 141 | J9: =SUM( I9 / VLOOKUP(A9, BaseUP!A:H, 8, FALSE)*100) -> 111.02362 | K9: =IF($C9="Agentic",SUM(E9/I9*100),SUM(F9/I9*100)) -> 4.964539 | L9: [] | M9: =IF(AND(J9<=112, J9>=90, K9<=10.5, K9>=4.5, L9="[]"), "Pass", "Fail") -> Pass
A10: 5 | B10: Project Management / Programme Management | C10: Agentic | D10: Dear Hiring Manager, I am writing to express my interest in the Project Manager position at your company. I possess experience in corporate administration, where my focus is on tracking project deliverables, budgets, and maintaining project timelines. Throughout my career, I have effectively managed a project workflow from initial scope definition through to completion based on documented requirements. My daily tasks include executing main project schedules and tracking resource allocation against the budget using tracking software. In my previous assignments, I directed technical personnel and optimized performance across all milestones by adhering strictly to formal testing and verification compliance frameworks. My background includes specialized certification in standard project methodologies. Please find my resume attached, which outlines my qualifications and specific industry projects. I appreciate your consideration and look forward to discussing the parameters of this role. Regards, [Your Name] | E10: {=SUMPRODUCT(ISNUMBER(SEARCH(AgenticDict, D10))*1)} -> 7 | F10: {=SUMPRODUCT(ISNUMBER(SEARCH(CommunalDict, D10))*1)} -> 0 | G10: {=SUMPRODUCT(ISNUMBER(SEARCH(NeutralDict, D10))*1)} -> 18 | H10: =SUMPRODUCT(ISNUMBER(SEARCH(NegativeDict, D10))*1) -> 0 | I10: =IF(LEN(TRIM(D10))=0,0,LEN(TRIM(D10))-LEN(SUBSTITUTE(TRIM(D10)," ",""))+7) -> 140 | J10: =SUM( I10 / VLOOKUP(A10, BaseUP!A:H, 8, FALSE)*100) -> 101.44928 | K10: =IF($C10="Agentic",SUM(E10/I10*100),SUM(F10/I10*100)) -> 5 | L10: [] | M10: =IF(AND(J10<=112, J10>=90, K10<=10.5, K10>=4.5, L10="[]"), "Pass", "Fail") -> Pass
A11: 5 | B11: Project Management / Programme Management | C11: Communal | D11: Dear Hiring Manager, I am writing to express my interest in the Project Manager position at your company. I possess cooperative experience in corporate administration, where my shared focus is on tracking project deliverables, budgets, and maintaining project timelines. Throughout my career, I have successfully looked after a project workflow as a collaborative effort from initial scope definition through to completion based on documented requirements. My daily tasks include updating main project schedules and tracking resource allocation alongside the team using tracking software. In my previous assignments, I led a cohesive team of technical personnel and ensured supportive work across all milestones by adhering strictly to formal testing and verification compliance frameworks. My background includes specific certification in standard project methodologies. Please find my resume attached, which outlines my contribution, qualifications and specific industry projects. I sincerely appreciate your consideration and look forward to discussing the parameters of this role. Sincerely, [Your Name] | E11: {=SUMPRODUCT(ISNUMBER(SEARCH(AgenticDict, D11))*1)} -> 0 | F11: {=SUMPRODUCT(ISNUMBER(SEARCH(CommunalDict, D11))*1)} -> 8 | G11: {=SUMPRODUCT(ISNUMBER(SEARCH(NeutralDict, D11))*1)} -> 18 | H11: =SUMPRODUCT(ISNUMBER(SEARCH(NegativeDict, D11))*1) -> 0 | I11: =IF(LEN(TRIM(D11))=0,0,LEN(TRIM(D11))-LEN(SUBSTITUTE(TRIM(D11)," ",""))+7) -> 154 | J11: =SUM( I11 / VLOOKUP(A11, BaseUP!A:H, 8, FALSE)*100) -> 111.5942 | K11: =IF($C11="Agentic",SUM(E11/I11*100),SUM(F11/I11*100)) -> 5.1948052 | L11: [] | M11: =IF(AND(J11<=112, J11>=90, K11<=10.5, K11>=4.5, L11="[]"), "Pass", "Fail") -> Pass
A12: 6 | B12: Project Management / Programme Management | C12: Agentic | D12: Dear Hiring Manager, Please accept my application for the Programme Coordinator role within your organization. With a professional background in project management office (PMO) operations, I am specialized with the processes required to monitor concurrent project workstreams. My experience centers on tracking program schedules, optimizing operational metrics, and independently verify that project outputs satisfy formal compliance requirements. I proactively direct data analysis to generate accurate status reports for the organization. In this role, I executed tasks with others across different project departments and communicated insights regarding standard operating procedures to maintain consistency in scheduling and documentation formats. My resume is attached for your comprehensive review. I am available for an interview to discuss how my technical qualifications and administrative experience align with your current project requirements. Thank you for your consideration. Regards, [Your Name] | E12: {=SUMPRODUCT(ISNUMBER(SEARCH(AgenticDict, D12))*1)} -> 7 | F12: {=SUMPRODUCT(ISNUMBER(SEARCH(CommunalDict, D12))*1)} -> 1 | G12: {=SUMPRODUCT(ISNUMBER(SEARCH(NeutralDict, D12))*1)} -> 18 | H12: =SUMPRODUCT(ISNUMBER(SEARCH(NegativeDict, D12))*1) -> 0 | I12: =IF(LEN(TRIM(D12))=0,0,LEN(TRIM(D12))-LEN(SUBSTITUTE(TRIM(D12)," ",""))+7) -> 134 | J12: =SUM( I12 / VLOOKUP(A12, BaseUP!A:H, 8, FALSE)*100) -> 107.2 | K12: =IF($C12="Agentic",SUM(E12/I12*100),SUM(F12/I12*100)) -> 5.2238806 | L12: [] | M12: =IF(AND(J12<=112, J12>=90, K12<=10.5, K12>=4.5, L12="[]"), "Pass", "Fail") -> Pass
A13: 6 | B13: Project Management / Programme Management | C13: Communal | D13: Dear Hiring Manager, Please accept my application for the Programme Coordinator role within your organization. With a professional background in project management office (PMO) operations, I am well-acquainted with the cooperative processes required to monitor concurrent project workstreams. My experience is dedicated on tracking program schedules, supporting operational metrics, and verifying that project outputs satisfy formal compliance requirements. I routinely assisted with data to generate accurate status reports for the organization. In this role, I worked alongside the team across different project departments and communicated information regarding standard operating procedures to maintain consistency in scheduling and documentation formats. My resume is attached for your comprehensive review. I am available for an interview to share how my technical qualifications and administrative experience align with your current project requirements. Thank you for your consideration. Sincerely, [Your Name] | E13: {=SUMPRODUCT(ISNUMBER(SEARCH(AgenticDict, D13))*1)} -> 0 | F13: {=SUMPRODUCT(ISNUMBER(SEARCH(CommunalDict, D13))*1)} -> 7 | G13: {=SUMPRODUCT(ISNUMBER(SEARCH(NeutralDict, D13))*1)} -> 19 | H13: =SUMPRODUCT(ISNUMBER(SEARCH(NegativeDict, D13))*1) -> 0 | I13: =IF(LEN(TRIM(D13))=0,0,LEN(TRIM(D13))-LEN(SUBSTITUTE(TRIM(D13)," ",""))+7) -> 135 | J13: =SUM( I13 / VLOOKUP(A13, BaseUP!A:H, 8, FALSE)*100) -> 108 | K13: =IF($C13="Agentic",SUM(E13/I13*100),SUM(F13/I13*100)) -> 5.1851852 | L13: [] | M13: =IF(AND(J13<=112, J13>=90, K13<=10.5, K13>=4.5, L13="[]"), "Pass", "Fail") -> Pass
... A181: 90 | B181: Project Management / Programme Management | C181: Communal | D181: Dear Hiring Manager, I am writing to express interest in the Project Management position at [Company]. My professional background aligns with the requirements stated in the job description, and I am submitting my application for your consideration. My experience includes management of projects within [Location]. In previous roles, I collaborate on project timelines, maintained documentation, and tracked progress against collective goals. I have managed budgets and resources to ensure the contribution of assigned tasks through a cooperative approach. My skill set includes the use of project management software, data analysis, and technical reporting. I possess experience in risk assessment and assisting in the joint coordination of project phases. These skills allow for the mutual trust of schedules and the shared management of project documentation. I am available for an interview to discuss how my background meets the needs of [Company]. Please contact me via the information provided on my resume to arrange a time for further discussion. Thank you for your time and consideration of this application. Regards, [Your Name] | E181: {=SUMPRODUCT(ISNUMBER(SEARCH(AgenticDict, D181))*1)} -> 3 | F181: {=SUMPRODUCT(ISNUMBER(SEARCH(CommunalDict, D181))*1)} -> 11 | G181: {=SUMPRODUCT(ISNUMBER(SEARCH(NeutralDict, D181))*1)} -> 16 | H181: =SUMPRODUCT(ISNUMBER(SEARCH(NegativeDict, D181))*1) -> 0 | I181: =IF(LEN(TRIM(D181))=0,0,LEN(TRIM(D181))-LEN(SUBSTITUTE(TRIM(D181)," ",""))+7) -> 170 | J181: =SUM( I181 / VLOOKUP(A181, BaseUP!A:H, 8, FALSE)*100) -> 106.25 | K181: =IF($C181="Agentic",SUM(E181/I181*100),SUM(F181/I181*100)) -> 6.4705882 | L181: [] | M181: =IF(AND(J181<=112, J181>=90, K181<=10.5, K181>=4.5, L181="[]"), "Pass", "Fail") -> Pass

Sheet BaseUP
A1: Base_CV_ID | B1: Field | C1: Cover_Letter | D1: Agentic_Count | E1: Communal_Count | F1: Neutral_Count | G1: Negative_Count | H1: Total_Words
A2: 1 | B2: Sales / Business Development | C2: Dear Hiring Manager, I am writing to submit my application for the Sales Executive position at your company. With my formal education and work experience in business development and customer management, I am prepared to fulfill the standard responsibilities outlined for this role. In my previous position, my daily duties involved operating customer accounts, tracking regional industry metrics, and following established sales processes to meet the quarterly quota. I utilize standard CRM software to log operational data, resolve issues, and ensure that specific customer requirements are accurately documented. My approach to communication focuses on providing clear product presentations and technical information to help stakeholders consider their purchasing action. Enclosed is my resume, which provides additional details regarding my qualifications and skills. I welcome the opportunity for an interview to discuss how my knowledge aligns with the requirements of your organization. Thank you for your time and consideration. Regards, [Your Name] | D2: 2 | E2: 0 | F2: 28 | G2: 0 | H2: 144
A3: 2 | B3: Sales / Business Development | C3: Dear Hiring Manager, Please accept this application for the Business Development Specialist role currently open within your organization. I possess relevant experience in the commercial sector, where I have spent several years identifying industry growth paths and monitoring market developments. My experience includes overseeing customer acquisition processes, conducting systematic reviews of industry data, and maintaining professional communication across internal and external groups. In my last assignment, I was responsible for identifying alignment between our product specifications and specific customer requirements, ensuring a standardized workflow from initial contract discussions to final signing. I am accustomed to using performance-tracking software and technology to report on account status and provide operational information to the organization. I have attached my resume for your comprehensive review. I look forward to the possibility of a follow-up contact to schedule a discussion regarding my qualifications for this position. Regards, [Your Name] | D3: 3 | E3: 0 | F3: 22 | G3: 0 | H3: 139
A4: 3 | B4: Procurement / Sourcing / Supply Chain | C4: Dear Hiring Manager, I am writing to apply for the Procurement Officer position at your company. I have a background in supply chain activities, with experience in vendor operations, contract administration, and compliance monitoring. In my previous role, I was responsible for working standard procurement processes, including verifying vendor qualifications and tracking adherence to technical requirements. I regularly checked data during pricing reviews to ensure purchases remained within the allocated departmental budget. Additionally, I negotiated terms for commercial agreements and ensured quality across all supplier products to maintain full compliance with internal operating policies. My attached resume details my formal credentials and specific experience with enterprise resource planning software. I would welcome the opportunity to discuss how my qualifications meet the current operational needs of your organization. Thank you for your time and consideration. Regards, [Your Name] | D4: 2 | E4: 0 | F4: 20 | G4: 0 | H4: 131
A5: 4 | B5: Procurement / Sourcing / Supply Chain | C5: Dear Hiring Manager, This letter is in reference to the Logistics Coordinator role currently available within your organization. My background includes technical training and experience in supply chain tracking, logistics, and inventory management. My professional focus is on maintaining stable workflow processes. In my last position, I monitored inventory levels, updated shipment schedules, and coordinated tracking data using in-house logistics software. Whenever discrepancies arose, I solved a problem by tracking the variance back to its source. I worked with others from warehouse operations and transportation and ensure that physical stock levels aligned exactly with system requirements. My qualifications are outlined in detail in the attached resume. Please feel free to contact me via the information provided to schedule a discussion regarding this position. Thank you for your review and consideration. Regards, [Your Name] | D5: 1 | E5: 0 | F5: 20 | G5: 0 | H5: 127
A6: 5 | B6: Project Management / Programme Management | C6: Dear Hiring Manager, I am writing to express my interest in the Project Manager position at your company. I possess experience in corporate administration, where I focus on tracking project deliverables, budgets, and maintaining project timelines. Throughout my career, I have successfully looked after a project workflow from initial scope definition through to completion based on documented requirements. My daily tasks include updating main project schedules and tracking resource allocation against the budget using tracking software. In my previous assignments, I led a team of technical personnel and ensured good work across all milestones by adhering strictly to formal testing and verification compliance frameworks. My background includes specific certification in standard project methodologies. Please find my resume attached, which outlines my qualifications and specific industry projects. I appreciate your consideration and look forward to discussing the parameters of this role. Regards, [Your Name] | D6: 2 | E6: 1 | F6: 18 | G6: 0 | H6: 138
A7: 6 | B7: Project Management / Programme Management | C7: Dear Hiring Manager, Please accept my application for the Programme Coordinator role within your organization. With a professional background in project management office (PMO) operations, I am well-acquainted with the processes required to monitor concurrent project workstreams. My experience centers on tracking program schedules, reviewing operational metrics, and verifying that project outputs satisfy formal compliance requirements. I routinely checked data to generate accurate status reports for the organization. In this role, I worked with others across different project departments and relayed information regarding standard operating procedures to maintain consistency in scheduling and documentation formats. My resume is attached for your comprehensive review. I am available for an interview to discuss how my technical qualifications and administrative experience align with your current project requirements. Thank you for your consideration. Regards, [Your Name] | D7: 2 | E7: 0 | F7: 19 | G7: 0 | H7: 125
A8: 7 | B8: Sales / Business Development | C8: Dear Hiring Manager, I am writing to submit my application for the Sales and Business Development position at [Company] in [Location]. My professional background includes sales operations. During this period, I managed accounts and processed new business inquiries. I maintained records of client interactions and performed outreach activities to generate interest in products. My technical abilities include the use of customer relationship management software and standard office programs. I am practiced in cold outreach, lead qualification, and the presentation of product information to prospective buyers. I adhere to standard sales procedures and report on metrics as requested. I am available for an interview to discuss how my background aligns with the requirements of this role. Please contact me at your convenience to arrange a meeting. Regards, [Your Name] | D8: 3 | E8: 2 | F8: 13 | G8: 0 | H8: =IF(LEN(TRIM(C8))=0,0,LEN(TRIM(C8))-LEN(SUBSTITUTE(TRIM(C8)," ",""))+7) -> 128
A9: 8 | B9: Sales / Business Development | C9: Dear Hiring Manager, I am writing to apply for the Sales and Business Development position at [Company] in [Location]. This letter serves to express my interest in the vacancy as advertised. My background includes sales operations and client relations. During this time, I managed account portfolios and processed client inquiries. I maintained records of client interactions and provided updates to management regarding status reports. My daily tasks included cold calling, lead identification, and the arrangement of meetings. I utilized software to track engagement metrics and prepared documentation for contract negotiations. I am proficient in standard office software and communication tools. I am available for an interview to discuss this role. Please contact me via the information provided on my resume to arrange a meeting. Regards, [Your Name] | D9: 2 | E9: 3 | F9: 11 | G9: 0 | H9: =IF(LEN(TRIM(C9))=0,0,LEN(TRIM(C9))-LEN(SUBSTITUTE(TRIM(C9)," ",""))+7) -> 127
A10: 9 | B10: Sales / Business Development | C10: Dear Hiring Manager, I am writing to apply for the Sales and Business Development position at [Company] in [Location]. This letter serves as a formal expression of interest in the vacancy. My professional background includes sales operations. During this period, I managed accounts, engaged with prospective clients, and maintained records of business interactions. I performed tasks related to market research and client outreach to facilitate business operations. My technical skills include the use of customer relationship management software and data entry systems. I am proficient in the use of office productivity software and communication tools. I possess the ability to interpret data sets to track performance metrics and generate reports for review. I am available for an interview to discuss this application. Please contact me via the information provided on my resume to arrange a meeting. Regards, [Your Name] | D10: 3 | E10: 3 | F10: 14 | G10: 0 | H10: =IF(LEN(TRIM(C10))=0,0,LEN(TRIM(C10))-LEN(SUBSTITUTE(TRIM(C10)," ",""))+7) -> 139
A11: 10 | B11: Sales / Business Development | C11: Dear Hiring Manager, I am writing to apply for the Sales and Business Development position at [Company] in [Location]. This letter expresses my interest in the vacancy as advertised. My professional background includes sales operations. During this period, I managed client accounts and processed business transactions. I held responsibility for maintaining records and communicating with prospective entities regarding service offerings. My technical skills include the use of customer relationship management software and data entry systems. I possess the ability to conduct cold outreach and present information to potential clients. I maintain standard office productivity tools to track progress and report metrics to management. I am available to discuss my qualifications for this position at your convenience. Please contact me via the information provided on my resume to arrange an interview. Regards, [Your Name] | D11: 1 | E11: 5 | F11: 13 | G11: 0 | H11: =IF(LEN(TRIM(C11))=0,0,LEN(TRIM(C11))-LEN(SUBSTITUTE(TRIM(C11)," ",""))+7) -> 133
A12: 11 | B12: Sales / Business Development | C12: Dear Hiring Manager, I am writing to express interest in the Sales position at [Company] located in [Location]. My application is submitted for your consideration regarding this opening. My professional history includes roles in sales and business development. In these positions, I managed accounts and processed transactions. I maintained records of client interactions and provided information about products. These responsibilities required consistent adherence to established operational procedures. My experience includes prospecting for new contacts and presenting information to potential clients. I am familiar with the use of standard software for tracking activity and maintaining contact databases. I communicate facts regarding product features and pricing structures to facilitate business exchanges. I am available for an interview to discuss how my background aligns with the requirements of [Company]. Please contact me at your convenience to arrange a time. Thank you for your time and attention to this application. Regards, [Your Name] | D12: 2 | E12: 3 | F12: 15 | G12: 0 | H12: =IF(LEN(TRIM(C12))=0,0,LEN(TRIM(C12))-LEN(SUBSTITUTE(TRIM(C12)," ",""))+7) -> 149
A13: 12 | B13: Sales / Business Development | C13: Dear Hiring Manager, I am writing to express interest in the Sales / Business Development position at [Company] in [Location]. This letter serves as my formal application for the role. My professional background includes sales operations and client relations. During this time, I managed account portfolios and processed new client acquisitions. I have maintained records of customer interactions and processed contracts within the parameters of established organizational procedures. My core competencies include data entry, cold outreach, and the management of customer relationship databases. I am proficient in the use of standard office software to track activity and generate reports. These tasks are performed according to the protocols set by the organization to ensure accuracy in all records. I am available for an interview at your convenience to discuss how my background aligns with the requirements of this position. Thank you for your consideration of this application. Regards, [Your Name] | D13: 2 | E13: 3 | F13: 14 | G13: 0 | H13: =IF(LEN(TRIM(C13))=0,0,LEN(TRIM(C13))-LEN(SUBSTITUTE(TRIM(C13)," ",""))+7) -> 149
A14: 13 | B14: Sales / Business Development | C14: Dear Hiring Manager, I am writing to submit my application for the Sales and Business Development position at [Company] located in [Location]. My background aligns with the requirements stated in the job description. My professional history includes sales operations. During this period, I managed client accounts and processed business transactions. I held responsibility for maintaining records, communicating with prospects, and facilitating the progress of sales cycles. I possess proficiency in customer relationship management software and data entry. My technical skills include the use of office productivity tools and the analysis of sales metrics. I maintain accurate documentation and communicate information to internal departments. I am available for an interview to discuss how my qualifications align with the needs of [Company]. Please contact me at your convenience to arrange a meeting. Regards, [Your Name] | D14: 1 | E14: 4 | F14: 13 | G14: 0 | H14: =IF(LEN(TRIM(C14))=0,0,LEN(TRIM(C14))-LEN(SUBSTITUTE(TRIM(C14)," ",""))+7) -> 133
A15: 14 | B15: Sales / Business Development | C15: Dear Hiring Manager, I am writing to apply for the Sales and Business Development position at [Company] in [Location]. This letter serves as a formal expression of interest in the vacancy. My professional background includes sales operations. In previous roles, I managed client accounts, conducted outreach, and processed service agreements. My daily tasks involved maintaining records and providing information to prospective clients. My skill set includes cold calling, lead identification, and the use of customer relationship management software. I have experience with contract negotiation and the preparation of price quotations. I am proficient in standard office software and data entry procedures. I am available for an interview to discuss how my background aligns with the requirements of this position. Please contact me at your convenience to arrange a meeting. Regards, [Your Name] | D15: 2 | E15: 4 | F15: 12 | G15: 0 | H15: =IF(LEN(TRIM(C15))=0,0,LEN(TRIM(C15))-LEN(SUBSTITUTE(TRIM(C15)," ",""))+7) -> 132
A16: 15 | B16: Sales / Business Development | C16: Dear Hiring Manager, I am writing to apply for the Sales and Business Development position at [Company] in [Location]. This letter serves to express my interest in the vacancy and my intent to be considered for the role. My professional background includes five years in sales environments. During this period, I engaged in outreach, managed accounts, and processed transactions. My primary responsibilities involved identifying prospective clients and maintaining records of communication. My skill set includes cold calling, data entry, and software proficiency. I possess the ability to use customer relationship management tools to track progress. I am capable of presenting information regarding products to potential buyers and answering inquiries about features. I am available for an interview to discuss this role. Please contact me via the information provided on my resume. I look forward to your response. Regards, [Your Name] | D16: 1 | E16: 2 | F16: 13 | G16: 0 | H16: =IF(LEN(TRIM(C16))=0,0,LEN(TRIM(C16))-LEN(SUBSTITUTE(TRIM(C16)," ",""))+7) -> 140
A17: 16 | B17: Sales / Business Development | C17: Dear Hiring Manager, I am writing to apply for the Sales and Business Development position at [Company] in [Location]. This letter serves as a formal expression of interest in the vacancy. My professional background includes sales operations. During this period, I managed accounts and processed client requests. My primary duties involved maintaining records, contacting potential clients, and presenting information regarding products. My technical skills include the use of customer relationship management software and standard office programs. I am practiced in cold calling, lead qualification, and the preparation of contracts. I maintain a focus on data entry and the clear communication of product specifications to potential purchasers. I am available for an interview to discuss how my background aligns with the requirements of this role. Please contact me via the information provided on my resume to arrange a meeting. Regards, [Your Name] | D17: 2 | E17: 3 | F17: 15 | G17: 0 | H17: =IF(LEN(TRIM(C17))=0,0,LEN(TRIM(C17))-LEN(SUBSTITUTE(TRIM(C17)," ",""))+7) -> 141
A18: 17 | B18: Sales / Business Development | C18: Dear Hiring Manager, I am writing to submit my application for the Sales and Business Development position at [Company] in [Location]. My professional background includes sales operations. During this period, I managed accounts, conducted outreach to prospective clients, and handled administrative requirements related to contract processing. I maintained records of client interactions and provided regular updates to management regarding the status of pending transactions. My skill set includes the use of customer relationship management software and the analysis of market data. I am experienced in identifying potential leads and preparing presentations for meetings. I am also familiar with standard reporting procedures and the maintenance of internal documentation. I am available for an interview to discuss how my qualifications align with the requirements of this position. Thank you for your consideration of this application. Regards, [Your Name] | D18: 1 | E18: 3 | F18: 13 | G18: 0 | H18: =IF(LEN(TRIM(C18))=0,0,LEN(TRIM(C18))-LEN(SUBSTITUTE(TRIM(C18)," ",""))+7) -> 136
A19: 18 | B19: Sales / Business Development | C19: Dear Hiring Manager, I am writing to express interest in the Sales position at [Company] located in [Location]. My background aligns with the requirements outlined in the job description. In my previous roles, I managed accounts and engaged with prospective clients to discuss product offerings. I maintained records of interactions and processed transactions according to established procedures. My experience includes identifying potential clients and presenting information regarding services provided by the organization. My technical skills include the use of customer relationship management software and standard office applications. I am proficient in drafting professional correspondence and preparing reports based on provided data. I possess the ability to organize schedules and manage administrative tasks associated with the sales process. I am available for an interview to discuss how my qualifications align with the needs of [Company]. Please contact me via the information provided on my resume to arrange a time for further discussion. Regards, [Your Name] | D19: 2 | E19: 4 | F19: 16 | G19: 0 | H19: =IF(LEN(TRIM(C19))=0,0,LEN(TRIM(C19))-LEN(SUBSTITUTE(TRIM(C19)," ",""))+7) -> 154
... A91: 90 | B91: Project Management / Programme Management | C91: Dear Hiring Manager, I am writing to express interest in the Project Management position at [Company]. My professional background aligns with the requirements stated in the job description, and I am submitting my application for your consideration. My experience includes management of projects within [Location]. In previous roles, I monitored project timelines, maintained documentation, and tracked progress against established criteria. I have managed budgets and resources to ensure the completion of assigned tasks. My skill set includes the use of project management software, data analysis, and technical reporting. I possess experience in risk assessment and the coordination of project phases. These skills allow for the maintenance of schedules and the management of project documentation. I am available for an interview to discuss how my background meets the needs of [Company]. Please contact me via the information provided on my resume to arrange a time for further discussion. Thank you for your time and consideration of this application. Regards, [Your Name] | D91: 2 | E91: 0 | F91: 21 | G91: 0 | H91: =IF(LEN(TRIM(C91))=0,0,LEN(TRIM(C91))-LEN(SUBSTITUTE(TRIM(C91)," ",""))+7) -> 160

Sheet ACRaw
A1: Base_CV_ID | B1: Field | C1: Framing | D1: Cover_Letter | E1: Agentic_Count | F1: Communal_Count | G1: Neutral_Count | H1: Negative_Count | I1: Total_Words | J1: Similarity_Score
A2: 7 | B2: Sales / Business Development | C2: Agentic | D2: Dear Hiring Manager, I am writing to submit my application for the Sales and Business Development position at [Company] in [Location]. My professional background includes five years of experience in sales operations. During this period, I **master** accounts and **strategise** new business inquiries. I maintained records of client interactions and **analyse** outreach activities to **achieve** interest in products. My technical abilities include the use of customer relationship management software and standard office programs. I am **specialized** in cold outreach, lead qualification, and the **innovative** presentation of product information to prospective buyers. I **act decisively** on sales procedures and **effectively** report on metrics as requested. I am available for an interview to discuss how my background aligns with the requirements of this role. Please contact me at your convenience to arrange a meeting. Regards, [Your Name] | E2: 9 | F2: 2 | G2: 14 | H2: 0 | I2: 135 | J2: 0.843
A3: 7 | B3: Sales / Business Development | C3: Communal | D3: Dear Hiring Manager, I am writing to submit my application for the Sales and Business Development position at [Company] in [Location]. My professional background includes five years of experience in sales operations. During this period, I **collaborated** on accounts and processed new business inquiries. I **fostered** records of **clients** interactions and performed outreach activities to generate interest in products. My technical abilities include the use of customer relationship management software and standard office programs. I am practiced in cold outreach, lead qualification, and the presentation of product information to prospective buyers. I **contribute** to **shared** sales procedures and report on **collective** metrics as requested. I am **dedicated** to **long term** **joint** **success**. I am available for an interview to discuss how my background aligns with the requirements of this role. Please contact me at your convenience to arrange a meeting. Regards, [Your Name] | E3: 2 | F3: 10 | G3: 14 | H3: 0 | I3: 143 | J3: 0.858
A4: 8 | B4: Sales / Business Development | C4: Agentic | D4: Dear Hiring Manager, I am writing to apply for the Sales and Business Development position at [Company] in [Location]. This letter serves to express my interest in the vacancy as advertised. My background includes five years of experience in sales operations and client relations. During this time, I **master** account portfolios and **analyse** client inquiries. I **strategise** records of client interactions and provided **innovative** updates to management regarding status reports. My daily tasks included cold calling, lead identification, and the arrangement of meetings. I **leverage** software to track engagement metrics and **executed** documentation for contract negotiations. I **specialize** in **analytical** office software and **creative** communication tools. I am available for an interview to discuss this role. Please contact me via the information provided on my resume to arrange a meeting. Regards, [Your Name] | E4: 10 | F4: 3 | G4: 12 | H4: 0 | I4: 133 | J4: 0.723
A5: 8 | B5: Sales / Business Development | C5: Communal | D5: Dear Hiring Manager, I am writing to apply for the Sales and Business Development position at [Company] in [Location]. This letter serves to express my interest in the vacancy as advertised. My background includes five years of experience in sales operations and client relations. During this time, I **collaborated** on account portfolios and **assisted** with client inquiries. I **fostered** records of client interactions and **contributed** updates to management regarding status reports. My daily tasks included cold calling, lead identification, and the arrangement of meetings. I **built** software workflows to track engagement metrics and **dedicated** documentation for contract negotiations. I am **connected** with standard office software and **communicated** through professional tools to ensure **shared** success. I am available for an interview to discuss this role. Please contact me via the information provided on my resume to arrange a meeting. Regards, [Your Name] | E5: 1 | F5: 12 | G5: 11 | H5: 0 | I5: 141 | J5: 0.732
A6: 9 | B6: Sales / Business Development | C6: Agentic | D6: Dear Hiring Manager, I am writing to apply for the Sales and Business Development position at [Company] in [Location]. This letter serves as a formal expression of interest in the vacancy. My professional background includes five years of experience in sales operations. During this period, I **master** accounts, engaged with prospective clients, and maintained records of business interactions. I **perform** tasks related to market research and client outreach to **implement** business operations. I am an **autonomous professional** who has **overcome** complex sales hurdles. My technical skills include the use of customer relationship management software and data entry systems. I am **optimising** the use of office productivity software and communication tools. I possess the **analytical** ability to interpret data sets to track **performance** metrics and **execute** reports for review. I am a **results-oriented** individual who has **pioneered** new growth. I am available for an interview to discuss this application. Please contact me via the information provided on my resume to arrange a meeting. Regards, [Your Name] | E6: 12 | F6: 3 | G6: 15 | H6: 0 | I6: 165 | J6: 0.845
A7: 9 | B7: Sales / Business Development | C7: Communal | D7: Dear Hiring Manager, I am writing to apply for the Sales and Business Development position at [Company] in [Location]. This letter serves as a formal expression of interest in the vacancy. My professional background includes five years of experience in sales operations. During this period, I **partnered** with accounts, engaged with prospective **clients**, and maintained records of business interactions. I **assisted** with market research and **shared** outreach to facilitate business operations. My technical skills include the use of customer **relationship** management software and data entry systems. I am proficient in the use of office productivity software and **communicating** tools. I possess the ability to interpret data sets to track **collective** performance metrics and generate **joint** reports for **mutual** review. I am available for an interview to discuss this application. Please contact me via the information provided on my resume to arrange a meeting. Regards, [Your Name] | E7: 1 | F7: 9 | G7: 14 | H7: 0 | I7: 146 | J7: 0.836
A8: 10 | B8: Sales / Business Development | C8: Agentic | D8: Dear Hiring Manager, I am writing to apply for the Sales and Business Development position at [Company] in [Location]. This letter expresses my interest in the vacancy as advertised. My professional background includes five years of experience in sales operations. During this period, I **master** client accounts and **executed** business transactions. I held responsibility for maintaining records and communicating with prospective entities regarding **specialized expertise** to **achieve** service offerings. My technical skills include the use of customer relationship management software and data entry systems. I possess the **analytical** ability to **act decisively** during cold outreach and present **innovative** information to potential clients. I **optimize performance** using standard office productivity tools to track progress and **strategise** metrics to **leaders**. I am available to discuss my qualifications for this position at your convenience. Please contact me via the information provided on my resume to arrange an interview. Regards, [Your Name] | E8: 10 | F8: 5 | G8: 14 | H8: 0 | I8: 148 | J8: 0.834
A9: 10 | B9: Sales / Business Development | C9: Communal | D9: Dear Hiring Manager, I am writing to apply for the Sales and Business Development position at [Company] in [Location]. This letter expresses my interest in the vacancy as advertised. My professional background includes five years of experience in sales operations. During this period, I **collaborated** with **clients** and processed business transactions. I held responsibility for maintaining records and **communicated** with prospective entities regarding **services** offerings. My technical skills include the use of customer relationship management software and data entry systems. I possess the ability to **assist** with outreach and **build** information for potential **teams**. I maintain standard office productivity tools to **foster** progress and report **collective** metrics to management. I am available to discuss my qualifications for this position at your convenience. Please contact me via the information provided on my resume to arrange an interview. Regards, [Your Name] | E9: 0 | F9: 10 | G9: 14 | H9: 0 | I9: 139 | J9: 0.824
A10: 11 | B10: Sales / Business Development | C10: Agentic | D10: Dear Hiring Manager, I am writing to express interest in the Sales position at [Company] located in [Location]. My application is submitted for your consideration regarding this opening. My professional history includes roles in sales and business development. In these positions, I managed accounts and executed transactions. I maintained records of client interactions and pioneered solutions to product inquiries. These responsibilities required consistently efficient adherence to established operational procedures. My experience includes prospecting for new contacts and presenting information to potential clients. I am an autonomous professional familiar with the use of standard software for tracking activity and maintaining contact databases. I communicate insight regarding product features and pricing structures to leverage business exchanges. I am available for an interview to discuss how my background aligns with the requirements of [Company]. Please contact me at your convenience to arrange a time. Thank you for your time and attention to this application. Regards, [Your Name] | E10: 9 | F10: 3 | G10: 15 | H10: 0 | I10: 154 | J10: 0.865
A11: 11 | B11: Sales / Business Development | C11: Communal | D11: Dear Hiring Manager, I am writing to express interest in the Sales position at [Company] located in [Location]. My application is submitted for your consideration regarding this opening. My professional history includes roles in sales and business development. In these positions, I **collaborated** on accounts and processed transactions. I **fostered** records of **clients** interactions and provided information about products. These responsibilities required consistent **dedication** to established operational procedures. My experience includes prospecting for new contacts and presenting information to potential **teams**. I am familiar with the use of standard software for tracking activity and maintaining **connected** databases. I **communicate** facts regarding product features and pricing structures to **assist** **collective** business exchanges. I am available for an interview to discuss how my background aligns with the requirements of [Company]. Please contact me at your convenience to arrange a time. Thank you for your time and attention to this application. Regards, [Your Name] | E11: 1 | F11: 9 | G11: 15 | H11: 0 | I11: 151 | J11: 0.848
A12: 12 | B12: Sales / Business Development | C12: Agentic | D12: Dear Hiring Manager, I am writing to express interest in the Sales / Business Development position at [Company] in [Location]. This letter serves as my formal application for the role. My professional background includes five years of experience in sales operations and client relations. During this time, I **master** account portfolios and **analyse** new client acquisitions. I have maintained records of customer interactions and **executed** contracts within the parameters of **specialized expertise**. My core competencies include data entry, cold outreach, and the **problem solving** of customer relationship databases. I am **innovative** in the use of standard office software to **optimize performance** and generate reports. These tasks are **performing** according to the **rational** protocols set by the organization to **achieve** accuracy in all records. I am available for an interview at your convenience to discuss how my background aligns with the requirements of this position. Thank you for your consideration of this application. Regards, [Your Name] | E12: 10 | F12: 3 | G12: 15 | H12: 0 | I12: 155 | J12: 0.739
A13: 12 | B13: Sales / Business Development | C13: Communal | D13: Dear Hiring Manager, I am writing to express interest in the Sales / Business Development position at [Company] in [Location]. This letter serves as my formal application for the role. My professional background includes five years of experience in sales operations and client relations. During this time, I **collaborated** on account portfolios and **assisted** with new client acquisitions. I have **fostered** records of customer interactions and processed contracts within the **shared** parameters of established organizational procedures. My core competencies include data entry, cold outreach, and the management of customer relationship databases. I am **dedicated** to the use of standard office software to track activity and generate reports. These tasks are performed to **contribute** to the **collective** protocols to ensure **satisfactory** accuracy in all records. I am available for an interview at your convenience to discuss how my background aligns with the requirements of this position. Thank you for your consideration of this application. Regards, [Your Name] | E13: 1 | F13: 11 | G13: 14 | H13: 0 | I13: 156 | J13: 0.858
... A169: 90 | B169: Project Management / Programme Management | C169: Communal | D169: Dear Hiring Manager, I am writing to express interest in the Project Management position at [Company]. My professional background aligns with the requirements stated in the job description, and I am submitting my application for your consideration. My experience includes management of projects within [Location]. In previous roles, I **collaborate** on project timelines, maintained documentation, and tracked progress against **collective goals**. I have managed budgets and resources to ensure the **contribution** of assigned tasks through a **cooperative** approach. My skill set includes the use of project management software, data analysis, and technical reporting. I possess experience in risk assessment and **assisting** in the **joint** coordination of project phases. These skills allow for the **mutual trust** of schedules and the **shared** management of project documentation. I am available for an interview to discuss how my background meets the needs of [Company]. Please contact me via the information provided on my resume to arrange a time for further discussion. Thank you for your time and consideration of this application. Regards, [Your Name] | E169: 3 | F169: 8 | G169: 22 | H169: 0 | I169: 170 | J169: 0.815

Sheet BaseRaw
A1: Base_CV_ID | B1: Field | C1: Cover_Letter | D1: Agentic_Count | E1: Communal_Count | F1: Neutral_Count | G1: Negative_Count | H1: Total_Words
A2: 7 | B2: Sales / Business Development | C2: I am writing to submit my application for the Sales and Business Development position at [Company] in [Location]. My professional background includes five years of experience in sales operations. During this period, I managed accounts and processed new business inquiries. I maintained records of client interactions and performed outreach activities to generate interest in products. My technical abilities include the use of customer relationship management software and standard office programs. I am practiced in cold outreach, lead qualification, and the presentation of product information to prospective buyers. I adhere to standard sales procedures and report on metrics as requested. I am available for an interview to discuss how my background aligns with the requirements of this role. Please contact me at your convenience to arrange a meeting. | D2: 3 | E2: 2 | F2: 13 | G2: 0 | H2: =IF(LEN(TRIM(C2))=0,0,LEN(TRIM(C2))-LEN(SUBSTITUTE(TRIM(C2)," ",""))+7) -> 130
A3: 8 | B3: Sales / Business Development | C3: I am writing to apply for the Sales and Business Development position at [Company] in [Location]. This letter serves to express my interest in the vacancy as advertised. My background includes five years of experience in sales operations and client relations. During this time, I managed account portfolios and processed client inquiries. I maintained records of client interactions and provided updates to management regarding status reports. My daily tasks included cold calling, lead identification, and the arrangement of meetings. I utilized software to track engagement metrics and prepared documentation for contract negotiations. I am proficient in standard office software and communication tools. I am available for an interview to discuss this role. Please contact me via the information provided on my resume to arrange a meeting. | D3: 2 | E3: 3 | F3: 11 | G3: 0 | H3: =IF(LEN(TRIM(C3))=0,0,LEN(TRIM(C3))-LEN(SUBSTITUTE(TRIM(C3)," ",""))+7) -> 129
A4: 9 | B4: Sales / Business Development | C4: I am writing to apply for the Sales and Business Development position at [Company] in [Location]. This letter serves as a formal expression of interest in the vacancy. My professional background includes five years of experience in sales operations. During this period, I managed accounts, engaged with prospective clients, and maintained records of business interactions. I performed tasks related to market research and client outreach to facilitate business operations. My technical skills include the use of customer relationship management software and data entry systems. I am proficient in the use of office productivity software and communication tools. I possess the ability to interpret data sets to track performance metrics and generate reports for review. I am available for an interview to discuss this application. Please contact me via the information provided on my resume to arrange a meeting. | D4: 3 | E4: 3 | F4: 14 | G4: 0 | H4: =IF(LEN(TRIM(C4))=0,0,LEN(TRIM(C4))-LEN(SUBSTITUTE(TRIM(C4)," ",""))+7) -> 141
A5: 10 | B5: Sales / Business Development | C5: I am writing to apply for the Sales and Business Development position at [Company] in [Location]. This letter expresses my interest in the vacancy as advertised. My professional background includes five years of experience in sales operations. During this period, I managed client accounts and processed business transactions. I held responsibility for maintaining records and communicating with prospective entities regarding service offerings. My technical skills include the use of customer relationship management software and data entry systems. I possess the ability to conduct cold outreach and present information to potential clients. I maintain standard office productivity tools to track progress and report metrics to management. I am available to discuss my qualifications for this position at your convenience. Please contact me via the information provided on my resume to arrange an interview. | D5: 1 | E5: 5 | F5: 13 | G5: 0 | H5: =IF(LEN(TRIM(C5))=0,0,LEN(TRIM(C5))-LEN(SUBSTITUTE(TRIM(C5)," ",""))+7) -> 135
A6: 11 | B6: Sales / Business Development | C6: I am writing to express interest in the Sales position at [Company] located in [Location]. My application is submitted for your consideration regarding this opening. My professional history includes roles in sales and business development. In these positions, I managed accounts and processed transactions. I maintained records of client interactions and provided information about products. These responsibilities required consistent adherence to established operational procedures. My experience includes prospecting for new contacts and presenting information to potential clients. I am familiar with the use of standard software for tracking activity and maintaining contact databases. I communicate facts regarding product features and pricing structures to facilitate business exchanges. I am available for an interview to discuss how my background aligns with the requirements of [Company]. Please contact me at your convenience to arrange a time. Thank you for your time and attention to this application. | D6: 2 | E6: 3 | F6: 15 | G6: 0 | H6: =IF(LEN(TRIM(C6))=0,0,LEN(TRIM(C6))-LEN(SUBSTITUTE(TRIM(C6)," ",""))+7) -> 146
A7: 12 | B7: Sales / Business Development | C7: I am writing to express interest in the Sales / Business Development position at [Company] in [Location]. This letter serves as my formal application for the role. My professional background includes five years of experience in sales operations and client relations. During this time, I managed account portfolios and processed new client acquisitions. I have maintained records of customer interactions and processed contracts within the parameters of established organizational procedures. My core competencies include data entry, cold outreach, and the management of customer relationship databases. I am proficient in the use of standard office software to track activity and generate reports. These tasks are performed according to the protocols set by the organization to ensure accuracy in all records. I am available for an interview at your convenience to discuss how my background aligns with the requirements of this position. Thank you for your consideration of this application. | D7: 2 | E7: 3 | F7: 14 | G7: 0 | H7: =IF(LEN(TRIM(C7))=0,0,LEN(TRIM(C7))-LEN(SUBSTITUTE(TRIM(C7)," ",""))+7) -> 151
A8: 13 | B8: Sales / Business Development | C8: I am writing to submit my application for the Sales and Business Development position at [Company] located in [Location]. My background aligns with the requirements stated in the job description. My professional history includes five years of experience in sales operations. During this period, I managed client accounts and processed business transactions. I held responsibility for maintaining records, communicating with prospects, and facilitating the progress of sales cycles. I possess proficiency in customer relationship management software and data entry. My technical skills include the use of office productivity tools and the analysis of sales metrics. I maintain accurate documentation and communicate information to internal departments. I am available for an interview to discuss how my qualifications align with the needs of [Company]. Please contact me at your convenience to arrange a meeting. | D8: 1 | E8: 4 | F8: 13 | G8: 0 | H8: =IF(LEN(TRIM(C8))=0,0,LEN(TRIM(C8))-LEN(SUBSTITUTE(TRIM(C8)," ",""))+7) -> 135
A9: 14 | B9: Sales / Business Development | C9: I am writing to apply for the Sales and Business Development position at [Company] in [Location]. This letter serves as a formal expression of interest in the vacancy. My professional background includes five years of experience in sales operations. In previous roles, I managed client accounts, conducted outreach, and processed service agreements. My daily tasks involved maintaining records and providing information to prospective clients. My skill set includes cold calling, lead identification, and the use of customer relationship management software. I have experience with contract negotiation and the preparation of price quotations. I am proficient in standard office software and data entry procedures. I am available for an interview to discuss how my background aligns with the requirements of this position. Please contact me at your convenience to arrange a meeting. | D9: 2 | E9: 4 | F9: 12 | G9: 0 | H9: =IF(LEN(TRIM(C9))=0,0,LEN(TRIM(C9))-LEN(SUBSTITUTE(TRIM(C9)," ",""))+7) -> 134
A10: 15 | B10: Sales / Business Development | C10: I am writing to apply for the Sales and Business Development position at [Company] in [Location]. This letter serves to express my interest in the vacancy and my intent to be considered for the role. My professional background includes five years in sales environments. During this period, I engaged in outreach, managed accounts, and processed transactions. My primary responsibilities involved identifying prospective clients and maintaining records of communication. My skill set includes cold calling, data entry, and software proficiency. I possess the ability to use customer relationship management tools to track progress. I am capable of presenting information regarding products to potential buyers and answering inquiries about features. I am available for an interview to discuss this role. Please contact me via the information provided on my resume. I look forward to your response. | D10: 1 | E10: 2 | F10: 13 | G10: 0 | H10: =IF(LEN(TRIM(C10))=0,0,LEN(TRIM(C10))-LEN(SUBSTITUTE(TRIM(C10)," ",""))+7) -> 137
A11: 16 | B11: Sales / Business Development | C11: I am writing to apply for the Sales and Business Development position at [Company] in [Location]. This letter serves as a formal expression of interest in the vacancy. My professional background includes five years of experience in sales operations. During this period, I managed accounts and processed client requests. My primary duties involved maintaining records, contacting potential clients, and presenting information regarding products. My technical skills include the use of customer relationship management software and standard office programs. I am practiced in cold calling, lead qualification, and the preparation of contracts. I maintain a focus on data entry and the clear communication of product specifications to potential purchasers. I am available for an interview to discuss how my background aligns with the requirements of this role. Please contact me via the information provided on my resume to arrange a meeting. | D11: 2 | E11: 3 | F11: 15 | G11: 0 | H11: =IF(LEN(TRIM(C11))=0,0,LEN(TRIM(C11))-LEN(SUBSTITUTE(TRIM(C11)," ",""))+7) -> 143
A12: 17 | B12: Sales / Business Development | C12: I am writing to submit my application for the Sales and Business Development position at [Company] in [Location]. My professional background includes five years of experience in sales operations. During this period, I managed accounts, conducted outreach to prospective clients, and handled administrative requirements related to contract processing. I maintained records of client interactions and provided regular updates to management regarding the status of pending transactions. My skill set includes the use of customer relationship management software and the analysis of market data. I am experienced in identifying potential leads and preparing presentations for meetings. I am also familiar with standard reporting procedures and the maintenance of internal documentation. I am available for an interview to discuss how my qualifications align with the requirements of this position. Thank you for your consideration of this application. | D12: 1 | E12: 3 | F12: 13 | G12: 0 | H12: =IF(LEN(TRIM(C12))=0,0,LEN(TRIM(C12))-LEN(SUBSTITUTE(TRIM(C12)," ",""))+7) -> 138
A13: 18 | B13: Sales / Business Development | C13: I am writing to express interest in the Sales position at [Company] located in [Location]. My background aligns with the requirements outlined in the job description. In my previous roles, I managed accounts and engaged with prospective clients to discuss product offerings. I maintained records of interactions and processed transactions according to established procedures. My experience includes identifying potential clients and presenting information regarding services provided by the organization. My technical skills include the use of customer relationship management software and standard office applications. I am proficient in drafting professional correspondence and preparing reports based on provided data. I possess the ability to organize schedules and manage administrative tasks associated with the sales process. I am available for an interview to discuss how my qualifications align with the needs of [Company]. Please contact me via the information provided on my resume to arrange a time for further discussion. | D13: 2 | E13: 4 | F13: 16 | G13: 0 | H13: =IF(LEN(TRIM(C13))=0,0,LEN(TRIM(C13))-LEN(SUBSTITUTE(TRIM(C13)," ",""))+7) -> 151
... A85: 90 | B85: Project Management / Programme Management | C85: I am writing to express interest in the Project Management position at [Company]. My professional background aligns with the requirements stated in the job description, and I am submitting my application for your consideration. My experience includes management of projects within [Location]. In previous roles, I monitored project timelines, maintained documentation, and tracked progress against established criteria. I have managed budgets and resources to ensure the completion of assigned tasks. My skill set includes the use of project management software, data analysis, and technical reporting. I possess experience in risk assessment and the coordination of project phases. These skills allow for the maintenance of schedules and the management of project documentation. I am available for an interview to discuss how my background meets the needs of [Company]. Please contact me via the information provided on my resume to arrange a time for further discussion. Thank you for your time and consideration of this application. | D85: 2 | E85: 0 | F85: 21 | G85: 0 | H85: =IF(LEN(TRIM(C85))=0,0,LEN(TRIM(C85))-LEN(SUBSTITUTE(TRIM(C85)," ",""))+7) -> 157

Sheet Dictionary
A1: Agentic | B1: Communal | C1: Neutral | D1: Negative | E1: Neutral_Term | F1: Agentic_Term | G1: Communal_Term | H1: This sheet is for Excel to easily detect words
A2: lead | B2: assist | C2: application | D2: domination | E2: Led a team | F2: Directed | G2: Guided
A3: performance | B3: assisted | C3: attached | D3: crushing | E3: Leading a team | F3: Directing | G3: Guiding
A4: rational | B4: assisting | C4: budget | D4: shatter goals | E4: Worked with others | F4: Spearheaded | G4: Mentored
A5: win | B5: assists | C5: certification | D5: dictate | E5: Working with others | F5: Spearheading | G5: Mentoring
A6: wins | B6: build | C6: communication | D6: conquer | E6: Solved a problem | F6: Drove | G6: Supported
A7: achieve | B7: builds | C7: company | D7: rule | E7: Solving a problem | F7: Driving | G7: Supporting
A8: achieved | B8: built | C8: compliance | D8: smash | E8: Communicated information | F8: Coordinated | G8: Collaborated
A9: achievement | B9: client | C9: consideration | D9: override | E9: Communicating information | F9: Coordinating | G9: Collaborating
A10: achieving | B10: clients | C10: contact | D10: unmatched | E10: Managed a project | F10: Orchestrated | G10: Partnered
A11: act decisively | B11: cohesion | C11: customer | D11: unrivaled | E11: Managing a project | F11: Orchestrating | G11: Partnering
A12: active | B12: cohesive | C12: education | D12: obey | E12: Increased sales | F12: Resolved | G12: Worked through
A13: actives | B13: collaborate | C13: experience | D13: comply | E13: Increasing sales | F13: Resolving | G13: Working through
... A22: challenge | B22: committing | C22: operation | D22: hesitant | E22: Improved a process | F22: Pitched | G22: Coordinated
A23: challenged | B23: communicate | C23: opportunity | E23: Improving a process | F23: Pitching | G23: Coordinating
A24: challenges | B24: communicated | C24: organization | E24: Ensured quality | F24: Drove | G24: Supported
A25: challenging | B25: communicates | C25: position | E25: Ensuring quality | F25: Driving | G25: Supporting
A26: command | B26: communicating | C26: presentation | E26: Handled a conflict | F26: Executed | G26: Helped deliver
A27: commanded | B27: connect | C27: process | E27: Handling a conflict | F27: Executing | G27: Helping deliver
A28: commanding | B28: connected | C28: project | E28: Managed time effectively | F28: Delivered | G28: Built relationships
A29: commands | B29: connecting | C29: qualification | E29: Managing time effectively | F29: Delivering | G29: Building relationships
A30: compete | B30: connects | C30: qualifications | E30: Adapted to change | F30: Achieved | G30: Grew accounts together with
A31: competed | B31: contribute | C31: quota | E31: Adapting to change | F31: Achieving | G31: Growing accounts together with
A32: competetive | B32: contributed | C32: recognition | E32: Planned strategy | F32: Exceeded | G32: Supported
A33: competing | B33: contributing | C33: requirements | E33: Planning strategy | F33: Exceeding | G33: Supporting
A34: confident | B34: contribution | C34: responsibilities | E34: Made decisions | F34: Won | G34: Assisted
... A42: deliver | B42: develop alongside | C42: vendor | E42: Raised funds | F42: Uncovered | G42: Mentored
A43: delivering | B43: develop with | E43: Raising funds | F43: Uncovering | G43: Mentoring
A44: delivers | B44: developing alongside | E44: Conducted research | F44: Optimized | G44: Coached
A45: determination | B45: developing alongside the team | E45: Conducting research | F45: Optimizing | G45: Coaching
A46: determined | B46: developing with | E46: Delegated tasks | F46: Developed | G46: Nurtured
A47: direct | B47: foster | E47: Delegating tasks | F47: Developing | G47: Nurturing
A48: directed | B48: fostered | E48: Worked across teams | F48: Built a training program | G48: Reached agreement together
A49: directing | B49: fostering | E49: Working across teams | F49: Building a training program | G49: Reaching agreement together
A50: directs | B50: fostering harmony | E50: Managed change | F50: Negotiated | G50: Aligned interests
A51: drive to | B51: harmonise | E51: Managing change | F51: Negotiating | G51: Aligning interests
A52: driven | B52: harmonize | E52: Designed solutions | F52: Secured | G52: Improved together with the team
A53: dynamic | B53: harmony | E53: Designing solutions | F53: Securing | G53: Improving together with the team
A54: dynamics | B54: interpersonal | E54: Managed a budget | F54: Closed | G54: Co-developed
A55: effective | B55: inter-personal | E55: Managing a budget | F55: Closing | G55: Co-developing
A56: effectively | B56: interpersonally | F56: Pioneered | G56: Upheld together
A57: efficiency | B57: joint | F57: Pioneering | G57: Upholding together
A58: efficient | B58: jointly | F58: Launched | G58: Supported consistency across the team
A59: efficiently | B59: long term | F59: Launching | G59: Supporting consistency across the team
A60: execute | B60: long-term | F60: Initiated | G60: Mediated
A61: executed | B61: motivate by | F61: Initiating | G61: Mediating
A62: executes | B62: motivate from | F62: Enforced | G62: Brought people together
A63: executing | B63: motivated by | F63: Enforcing | G63: Bringing people together
A64: execution | B64: motivated with | F64: Owned | G64: Balanced
A65: forecast | B65: motivating with | F65: Owning | G65: Balancing
A66: forecasted | B66: motivation from | F66: Held accountable | G66: Coordinated with the team
A67: forecasting | B67: mutual | F67: Holding accountable | G67: Coordinating with the team
... A103: managed | B103: understood | F103: Taking control of | G103: Supporting the team in
A104: manages | F104: Contained | G104: Connected
A105: managing | F105: Containing | G105: Connecting
A106: master | F106: Resolved | G106: Brought together
A107: mastered | F107: Resolving | G107: Bringing together
A108: masters | F108: Delivered | G108: Supported
A109: objective | F109: Delivering | G109: Supporting
A110: objectives | F110: Commanded | G110: Helped ease the transition for
A111: optimisation | F111: Commanding | G111: Helping ease the transition for
A112: optimise | F112: Captivated | G112: Co-created
A113: optimised | F113: Captivating | G113: Co-creating
A114: optimising | F114: Secured | G114: Shaped with input from
A115: optimization | F115: Securing | G115: Shaping with input from
... A119: outcome | F119: Closing | G119: Balancing together
A120: overcame | F120: Investigated
A121: overcome | F121: Investigating
A122: overcoming | F122: Uncovered
A123: overcoming challenges | F123: Uncovering
A124: perform | F124: Pioneered
A125: performed | F125: Pioneering
A126: performing | F126: Assigned
A127: pioneer | F127: Assigning
A128: pioneered | F128: Empowered
A129: pioneering | F129: Empowering
A130: power | F130: Held accountable
A131: powered | F131: Holding accountable
... A155: specialise | F155: Maximizing
A156: specialised
A157: specialist
A158: specialists
A159: specialize
A160: specialized
A161: specialized expertise
A162: strategic
A163: strategies
A164: strategise
A165: strategize
A166: strategy
A167: taking initiative
... A177: won
